CHANGES.yaml
LICENSE
MANIFEST.in
Makefile
README.rst
setup.py
bin/cdent
cdent/__init__.py
cdent/ast.py
cdent/command.py
cdent/compiler.py
cdent/grammar.py
cdent/runtime.py
cdent/test.py
cdent.egg-info/PKG-INFO
cdent.egg-info/SOURCES.txt
cdent.egg-info/dependency_links.txt
cdent.egg-info/requires.txt
cdent.egg-info/top_level.txt
cdent/emitter/__init__.py
cdent/emitter/actionscript.py
cdent/emitter/go.py
cdent/emitter/java.py
cdent/emitter/javascript.py
cdent/emitter/perl.py
cdent/emitter/perl6.py
cdent/emitter/php.py
cdent/emitter/pir.py
cdent/emitter/python.py
cdent/emitter/python3.py
cdent/emitter/ruby.py
cdent/emitter/scala.py
cdent/emitter/cdent/__init__.py
cdent/emitter/cdent/yaml.py
cdent/parser/__init__.py
cdent/parser/base/__init__.py
cdent/parser/base/grammar.py
cdent/parser/cdent/__init__.py
cdent/parser/cdent/yaml.py
cdent/parser/javascript/__init__.py
cdent/parser/javascript/grammar.py
cdent/parser/perl/__init__.py
cdent/parser/perl/grammar.py
cdent/parser/perl6/__init__.py
cdent/parser/perl6/grammar.py
cdent/parser/pir/__init__.py
cdent/parser/pir/grammar.py
cdent/parser/python/__init__.py
cdent/parser/python/grammar.py
package/__init__.py
package/__init__.pyc
package/errors.py
package/errors.pyc
package/info.py
package/info.pyc
package/info.yaml
package/unittest.py
tests/test_commands.py
tests/test_emit.py
tests/test_parse_javascript.py
tests/test_parse_perl6.py
tests/test_parse_pir.py
tests/test_parse_python.py
tests/modules/World.as
tests/modules/World.cd.js
tests/modules/World.cd.pir
tests/modules/World.cd.pm6
tests/modules/World.cd.yaml
tests/modules/World.go
tests/modules/World.java
tests/modules/World.js
tests/modules/World.php
tests/modules/World.pir
tests/modules/World.pm
tests/modules/World.pm6
tests/modules/World.rb
tests/modules/World.scala
tests/modules/world.cd.py
tests/modules/world.py
tests/modules/world.py3