Metadata-Version: 1.0
Name: cdent
Version: 0.5.7
Summary: C'Dent - A Portable Module Programming Language
Home-page: http://www.cdent.org/
Author: Ingy dot Net
Author-email: ingy@ingy.net
License: UNKNOWN
Platform: UNKNOWN
Classifier: Development Status :: 2 - Pre-Alpha
Classifier: Environment :: Console
Classifier: Intended Audience :: Developers
Classifier: License :: OSI Approved :: BSD License
Classifier: Programming Language :: Awk
Classifier: Programming Language :: C#
Classifier: Programming Language :: C++
Classifier: Programming Language :: Erlang
Classifier: Programming Language :: Haskell
Classifier: Programming Language :: Java
Classifier: Programming Language :: JavaScript
Classifier: Programming Language :: Other Scripting Engines
Classifier: Programming Language :: Perl
Classifier: Programming Language :: PHP
Classifier: Programming Language :: Python
Classifier: Programming Language :: Ruby
Classifier: Programming Language :: Scheme
Classifier: Programming Language :: Tcl
Classifier: Topic :: Software Development
Classifier: Topic :: System :: Software Distribution
Classifier: Topic :: Utilities
